{
  "country": "Germany",
  "countryCode": "GER",
  "confederation": "UEFA",
  "year": 1990,
  "tournamentId": "wc-1990",
  "players": [
    {
      "id": "ger90-illgner",
      "name": "Bodo Illgner",
      "position": "POR",
      "altPositions": [],
      "stats": { "reflejos": 89, "manejo": 87, "salidas": 85, "penales": 86, "distribucion": 82 },
      "rating": 88,
      "country": "Germany",
      "tournamentYear": 1990,
      "tournamentId": "wc-1990",
      "club": "1. FC Köln",
      "goals": 0,
      "isCaptain": false
    },
    {
      "id": "ger90-aumann",
      "name": "Raimond Aumann",
      "position": "POR",
      "altPositions": [],
      "stats": { "reflejos": 81, "manejo": 80, "salidas": 79, "penales": 77, "distribucion": 78 },
      "rating": 80,
      "country": "Germany",
      "tournamentYear": 1990,
      "tournamentId": "wc-1990",
      "club": "Bayern München",
      "goals": 0,
      "isCaptain": false
    },
    {
      "id": "ger90-kohler",
      "name": "Jürgen Kohler",
      "position": "DFC",
      "altPositions": [{ "position": "MCD", "compatibility": "puede" }],
      "stats": { "defAerea": 90, "intercepciones": 88, "velocidad": 85, "pases": 80, "duelos": 91 },
      "rating": 89,
      "country": "Germany",
      "tournamentYear": 1990,
      "tournamentId": "wc-1990",
      "club": "FC Bayern München",
      "goals": 0,
      "isCaptain": false
    },
    {
      "id": "ger90-augenthaler",
      "name": "Klaus Augenthaler",
      "position": "DFC",
      "altPositions": [{ "position": "MCD", "compatibility": "puede" }],
      "stats": { "defAerea": 85, "intercepciones": 83, "velocidad": 78, "pases": 82, "duelos": 85 },
      "rating": 83,
      "country": "Germany",
      "tournamentYear": 1990,
      "tournamentId": "wc-1990",
      "club": "Bayern München",
      "goals": 0,
      "isCaptain": false
    },
    {
      "id": "ger90-buchwald",
      "name": "Guido Buchwald",
      "position": "DFC",
      "altPositions": [{ "position": "MCD", "compatibility": "natural" }],
      "stats": { "defAerea": 86, "intercepciones": 85, "velocidad": 82, "pases": 81, "duelos": 87 },
      "rating": 85,
      "country": "Germany",
      "tournamentYear": 1990,
      "tournamentId": "wc-1990",
      "club": "VfB Stuttgart",
      "goals": 1,
      "isCaptain": false
    },
    {
      "id": "ger90-brehme",
      "name": "Andreas Brehme",
      "position": "LI",
      "altPositions": [{ "position": "LD", "compatibility": "natural" }],
      "stats": { "defAerea": 86, "intercepciones": 84, "velocidad": 85, "pases": 87, "duelos": 85 },
      "rating": 88,
      "country": "Germany",
      "tournamentYear": 1990,
      "tournamentId": "wc-1990",
      "club": "Inter Milan",
      "goals": 1,
      "isCaptain": false
    },
    {
      "id": "ger90-reuter",
      "name": "Stefan Reuter",
      "position": "LD",
      "altPositions": [{ "position": "MCD", "compatibility": "natural" }],
      "stats": { "defAerea": 83, "intercepciones": 82, "velocidad": 86, "pases": 83, "duelos": 84 },
      "rating": 84,
      "country": "Germany",
      "tournamentYear": 1990,
      "tournamentId": "wc-1990",
      "club": "FC Bayern München",
      "goals": 0,
      "isCaptain": false
    },
    {
      "id": "ger90-berthold",
      "name": "Thomas Berthold",
      "position": "LD",
      "altPositions": [{ "position": "DFC", "compatibility": "natural" }],
      "stats": { "defAerea": 83, "intercepciones": 81, "velocidad": 82, "pases": 80, "duelos": 83 },
      "rating": 82,
      "country": "Germany",
      "tournamentYear": 1990,
      "tournamentId": "wc-1990",
      "club": "AS Roma",
      "goals": 0,
      "isCaptain": false
    },
    {
      "id": "ger90-matthaus",
      "name": "Lothar Matthäus",
      "position": "MC",
      "altPositions": [{ "position": "MCD", "compatibility": "natural" }, { "position": "MCO", "compatibility": "puede" }],
      "stats": { "pases": 93, "vision": 92, "llegada": 94, "recuperacion": 91, "tecnica": 93 },
      "rating": 95,
      "country": "Germany",
      "tournamentYear": 1990,
      "tournamentId": "wc-1990",
      "club": "Inter Milan",
      "goals": 4,
      "isCaptain": true
    },
    {
      "id": "ger90-hassler",
      "name": "Thomas Häßler",
      "position": "MCD",
      "altPositions": [{ "position": "MC", "compatibility": "natural" }],
      "stats": { "recuperacion": 86, "pases": 87, "posicionamiento": 85, "duelos": 84, "resistencia": 87 },
      "rating": 86,
      "country": "Germany",
      "tournamentYear": 1990,
      "tournamentId": "wc-1990",
      "club": "Juventus",
      "goals": 1,
      "isCaptain": false
    },
    {
      "id": "ger90-bein",
      "name": "Uwe Bein",
      "position": "MCO",
      "altPositions": [{ "position": "MC", "compatibility": "natural" }],
      "stats": { "vision": 87, "paseFiltrado": 86, "llegada": 84, "regate": 83, "disparo": 84 },
      "rating": 85,
      "country": "Germany",
      "tournamentYear": 1990,
      "tournamentId": "wc-1990",
      "club": "Eintracht Frankfurt",
      "goals": 1,
      "isCaptain": false
    },
    {
      "id": "ger90-moller",
      "name": "Andreas Möller",
      "position": "MC",
      "altPositions": [{ "position": "MCO", "compatibility": "natural" }, { "position": "ED", "compatibility": "puede" }],
      "stats": { "pases": 86, "vision": 87, "llegada": 87, "recuperacion": 80, "tecnica": 88 },
      "rating": 86,
      "country": "Germany",
      "tournamentYear": 1990,
      "tournamentId": "wc-1990",
      "club": "Borussia Dortmund",
      "goals": 0,
      "isCaptain": false
    },
    {
      "id": "ger90-littbarski",
      "name": "Pierre Littbarski",
      "position": "ED",
      "altPositions": [{ "position": "MCO", "compatibility": "natural" }, { "position": "EI", "compatibility": "puede" }],
      "stats": { "velocidad": 87, "regate": 88, "centro": 85, "disparo": 83, "desmarque": 86 },
      "rating": 86,
      "country": "Germany",
      "tournamentYear": 1990,
      "tournamentId": "wc-1990",
      "club": "1. FC Köln",
      "goals": 0,
      "isCaptain": false
    },
    {
      "id": "ger90-thon",
      "name": "Olaf Thon",
      "position": "MC",
      "altPositions": [{ "position": "MCD", "compatibility": "puede" }],
      "stats": { "pases": 83, "vision": 82, "llegada": 83, "recuperacion": 82, "tecnica": 83 },
      "rating": 83,
      "country": "Germany",
      "tournamentYear": 1990,
      "tournamentId": "wc-1990",
      "club": "Bayern München",
      "goals": 0,
      "isCaptain": false
    },
    {
      "id": "ger90-flick",
      "name": "Hansi Flick",
      "position": "MC",
      "altPositions": [{ "position": "MCD", "compatibility": "puede" }],
      "stats": { "pases": 78, "vision": 77, "llegada": 76, "recuperacion": 79, "tecnica": 76 },
      "rating": 77,
      "country": "Germany",
      "tournamentYear": 1990,
      "tournamentId": "wc-1990",
      "club": "Bayern München",
      "goals": 0,
      "isCaptain": false
    },
    {
      "id": "ger90-klinsmann",
      "name": "Jürgen Klinsmann",
      "position": "DC",
      "altPositions": [{ "position": "EI", "compatibility": "puede" }],
      "stats": { "definicion": 91, "fisico": 85, "velocidad": 90, "cabezazo": 87, "pressing": 86, "desmarque": 92 },
      "rating": 91,
      "country": "Germany",
      "tournamentYear": 1990,
      "tournamentId": "wc-1990",
      "club": "Inter Milan",
      "goals": 3,
      "isCaptain": false
    },
    {
      "id": "ger90-voller",
      "name": "Rudi Völler",
      "position": "DC",
      "altPositions": [],
      "stats": { "definicion": 89, "fisico": 84, "velocidad": 85, "cabezazo": 86, "pressing": 85, "desmarque": 89 },
      "rating": 89,
      "country": "Germany",
      "tournamentYear": 1990,
      "tournamentId": "wc-1990",
      "club": "AS Roma",
      "goals": 3,
      "isCaptain": false
    },
    {
      "id": "ger90-riedle",
      "name": "Karl-Heinz Riedle",
      "position": "DC",
      "altPositions": [],
      "stats": { "definicion": 84, "fisico": 82, "velocidad": 84, "cabezazo": 85, "pressing": 80, "desmarque": 83 },
      "rating": 83,
      "country": "Germany",
      "tournamentYear": 1990,
      "tournamentId": "wc-1990",
      "club": "Werder Bremen",
      "goals": 0,
      "isCaptain": false
    },
    {
      "id": "ger90-gotz",
      "name": "Falko Götz",
      "position": "DC",
      "altPositions": [{ "position": "EI", "compatibility": "puede" }],
      "stats": { "definicion": 75, "fisico": 76, "velocidad": 78, "cabezazo": 74, "pressing": 73, "desmarque": 75 },
      "rating": 74,
      "country": "Germany",
      "tournamentYear": 1990,
      "tournamentId": "wc-1990",
      "club": "Bayer Leverkusen",
      "goals": 0,
      "isCaptain": false
    },
    {
      "id": "ger90-kruse",
      "name": "Axel Kruse",
      "position": "DC",
      "altPositions": [],
      "stats": { "definicion": 73, "fisico": 75, "velocidad": 74, "cabezazo": 73, "pressing": 72, "desmarque": 74 },
      "rating": 73,
      "country": "Germany",
      "tournamentYear": 1990,
      "tournamentId": "wc-1990",
      "club": "Hamburger SV",
      "goals": 0,
      "isCaptain": false
    },
    {
      "id": "ger90-kinkel",
      "name": "Klaus Kinkel",
      "position": "DC",
      "altPositions": [],
      "stats": { "definicion": 76, "fisico": 77, "velocidad": 75, "cabezazo": 76, "pressing": 74, "desmarque": 77 },
      "rating": 76,
      "country": "Germany",
      "tournamentYear": 1990,
      "tournamentId": "wc-1990",
      "club": "1. FC Kaiserslautern",
      "goals": 0,
      "isCaptain": false
    },
    {
      "id": "ger90-binz",
      "name": "Günter Hermann",
      "position": "POR",
      "altPositions": [],
      "stats": { "reflejos": 76, "manejo": 75, "salidas": 74, "penales": 73, "distribucion": 74 },
      "rating": 75,
      "country": "Germany",
      "tournamentYear": 1990,
      "tournamentId": "wc-1990",
      "club": "Hamburger SV",
      "goals": 0,
      "isCaptain": false
    },
    {
      "id": "ger90-sammer",
      "name": "Matthias Sammer",
      "position": "MCD",
      "altPositions": [{ "position": "DFC", "compatibility": "puede" }, { "position": "MC", "compatibility": "natural" }],
      "stats": { "recuperacion": 84, "pases": 85, "posicionamiento": 84, "duelos": 83, "resistencia": 84 },
      "rating": 84,
      "country": "Germany",
      "tournamentYear": 1990,
      "tournamentId": "wc-1990",
      "club": "VfB Stuttgart",
      "goals": 0,
      "isCaptain": false
    }
  ]
}
